pnplabs/__init__.py
pnplabs/__main__.py
pnplabs/main_entry_point.py
pnplabs/functions/__init__.py
pnplabs/functions/connect.py
pnplabs/functions/dynamic.py
pnplabs/functions/get_commands_cache.py
pnplabs/functions/get_config.py
pnplabs/functions/instructions.py
pnplabs/functions/verify_path.py
pnplabs/utils/__init__.py
pnplabs/utils/add_py_scripts_to_path.py
pnplabs/utils/commands.py
pnplabs/utils/firestore.py
pnplabs/utils/local_commands_cache.py
pnplabs/utils/local_config.py
pnplabs-1.0.19.dist-info/LICENSE
pnplabs-1.0.19.dist-info/METADATA
pnplabs-1.0.19.dist-info/WHEEL
pnplabs-1.0.19.dist-info/entry_points.txt
pnplabs-1.0.19.dist-info/top_level.txt
pnplabs-1.0.19.dist-info/RECORD
