Metadata-Version: 2.1
Name: pnplabs
Version: 1.0.19
Summary: pnplabs.io main package
Home-page: https://pnplabs.io
Author: pnplabs
Author-email: anything@pnplabs.io
License: UNKNOWN
Platform: UNKNOWN
Classifier: Programming Language :: Python :: 3
Classifier: License :: OSI Approved :: MIT License
Classifier: Operating System :: OS Independent
Requires-Python: >=3.6
Requires-Dist: appdirs
Requires-Dist: requests
Requires-Dist: google-auth
Requires-Dist: google-cloud-firestore
Requires-Dist: windows-path-adder
